minekuai/__init__.py
minekuai/minekuai.py
minekuai-0.0.4.dist-info/METADATA
minekuai-0.0.4.dist-info/WHEEL
minekuai-0.0.4.dist-info/top_level.txt
minekuai-0.0.4.dist-info/RECORD
