Metadata-Version: 2.1
Name: minekuai
Version: 0.0.4
Summary: minekuai request library
Author: SCH
Requires-Python: >=3.6
